qforms/__init__.py
qforms/readme.md
qforms/templates/conta.html
qforms-0.0.4.dist-info/entry_points.txt
qforms-0.0.4.dist-info/WHEEL
qforms-0.0.4.dist-info/METADATA
qforms-0.0.4.dist-info/RECORD
