Metadata-Version: 2.4
Name: qforms
Version: 0.0.4
Summary: Qforms: google-forms like local form generator tool
Keywords: forms,flask,privacy
Author-email: João Alvim <joaoalvim179@proton.me>, JJoao <jj@di.uminho.pt>
Requires-Dist: flask
Requires-Dist: waitress
Requires-Dist: pyyaml
Requires-Dist: jjcli
Project-URL: Bug Tracker, https://github.com/jotaalvim/qforms/issues
Project-URL: repository, https://github.com/jotaalvim/qforms
